<annotation>
	<folder></folder>
	<filename>20200714_161249_jpg.rf.3d9f5810fbe11d97efb4f6fbc393aa49.jpg</filename>
	<path>20200714_161249_jpg.rf.3d9f5810fbe11d97efb4f6fbc393aa49.jpg</path>
	<source>
		<database>roboflow.ai</database>
	</source>
	<size>
		<width>1000</width>
		<height>400</height>
		<depth>3</depth>
	</size>
	<segmented>0</segmented>
	<object>
		<name>cmc7</name>
		<pose>Unspecified</pose>
		<truncated>0</truncated>
		<difficult>0</difficult>
		<occluded>0</occluded>
		<bndbox>
			<xmin>228</xmin>
			<xmax>651</xmax>
			<ymin>245</ymin>
			<ymax>290</ymax>
		</bndbox>
	</object>
	<object>
		<name>cmc7box</name>
		<pose>Unspecified</pose>
		<truncated>0</truncated>
		<difficult>0</difficult>
		<occluded>0</occluded>
		<bndbox>
			<xmin>731</xmin>
			<xmax>846</xmax>
			<ymin>75</ymin>
			<ymax>146</ymax>
		</bndbox>
	</object>
	<object>
		<name>sucnum</name>
		<pose>Unspecified</pose>
		<truncated>0</truncated>
		<difficult>0</difficult>
		<occluded>0</occluded>
		<bndbox>
			<xmin>755</xmin>
			<xmax>844</xmax>
			<ymin>137</ymin>
			<ymax>159</ymax>
		</bndbox>
	</object>
	<object>
		<name>sucnum</name>
		<pose>Unspecified</pose>
		<truncated>0</truncated>
		<difficult>0</difficult>
		<occluded>0</occluded>
		<bndbox>
			<xmin>457</xmin>
			<xmax>587</xmax>
			<ymin>78</ymin>
			<ymax>104</ymax>
		</bndbox>
	</object>
	<object>
		<name>sucnum</name>
		<pose>Unspecified</pose>
		<truncated>0</truncated>
		<difficult>0</difficult>
		<occluded>0</occluded>
		<bndbox>
			<xmin>524</xmin>
			<xmax>621</xmax>
			<ymin>62</ymin>
			<ymax>78</ymax>
		</bndbox>
	</object>
	<object>
		<name>bank</name>
		<pose>Unspecified</pose>
		<truncated>0</truncated>
		<difficult>0</difficult>
		<occluded>0</occluded>
		<bndbox>
			<xmin>125</xmin>
			<xmax>222</xmax>
			<ymin>59</ymin>
			<ymax>266</ymax>
		</bndbox>
	</object>
	<object>
		<name>accnum</name>
		<pose>Unspecified</pose>
		<truncated>0</truncated>
		<difficult>0</difficult>
		<occluded>0</occluded>
		<bndbox>
			<xmin>292</xmin>
			<xmax>412</xmax>
			<ymin>196</ymin>
			<ymax>213</ymax>
		</bndbox>
	</object>
</annotation>
