<annotation>
	<folder></folder>
	<filename>20200714_152120_jpg.rf.500bbe4d5ea8fb99ddd2c4f524724685.jpg</filename>
	<path>20200714_152120_jpg.rf.500bbe4d5ea8fb99ddd2c4f524724685.jpg</path>
	<source>
		<database>roboflow.ai</database>
	</source>
	<size>
		<width>1000</width>
		<height>400</height>
		<depth>3</depth>
	</size>
	<segmented>0</segmented>
	<object>
		<name>cmc7</name>
		<pose>Unspecified</pose>
		<truncated>0</truncated>
		<difficult>0</difficult>
		<occluded>0</occluded>
		<bndbox>
			<xmin>258</xmin>
			<xmax>622</xmax>
			<ymin>263</ymin>
			<ymax>286</ymax>
		</bndbox>
	</object>
	<object>
		<name>cmc7box</name>
		<pose>Unspecified</pose>
		<truncated>0</truncated>
		<difficult>0</difficult>
		<occluded>0</occluded>
		<bndbox>
			<xmin>686</xmin>
			<xmax>801</xmax>
			<ymin>125</ymin>
			<ymax>169</ymax>
		</bndbox>
	</object>
	<object>
		<name>sucnum</name>
		<pose>Unspecified</pose>
		<truncated>0</truncated>
		<difficult>0</difficult>
		<occluded>0</occluded>
		<bndbox>
			<xmin>445</xmin>
			<xmax>544</xmax>
			<ymin>123</ymin>
			<ymax>142</ymax>
		</bndbox>
	</object>
	<object>
		<name>sucnum</name>
		<pose>Unspecified</pose>
		<truncated>0</truncated>
		<difficult>0</difficult>
		<occluded>0</occluded>
		<bndbox>
			<xmin>512</xmin>
			<xmax>590</xmax>
			<ymin>108</ymin>
			<ymax>123</ymax>
		</bndbox>
	</object>
	<object>
		<name>sucnum</name>
		<pose>Unspecified</pose>
		<truncated>0</truncated>
		<difficult>0</difficult>
		<occluded>0</occluded>
		<bndbox>
			<xmin>705</xmin>
			<xmax>790</xmax>
			<ymin>168</ymin>
			<ymax>186</ymax>
		</bndbox>
	</object>
	<object>
		<name>bank</name>
		<pose>Unspecified</pose>
		<truncated>0</truncated>
		<difficult>0</difficult>
		<occluded>0</occluded>
		<bndbox>
			<xmin>172</xmin>
			<xmax>241</xmax>
			<ymin>112</ymin>
			<ymax>263</ymax>
		</bndbox>
	</object>
	<object>
		<name>accnum</name>
		<pose>Unspecified</pose>
		<truncated>0</truncated>
		<difficult>0</difficult>
		<occluded>0</occluded>
		<bndbox>
			<xmin>310</xmin>
			<xmax>415</xmax>
			<ymin>218</ymin>
			<ymax>230</ymax>
		</bndbox>
	</object>
</annotation>
