<annotation>
	<folder></folder>
	<filename>cheque_jpg.rf.5c4d57d9ad5202c42739e89d016acdfc.jpg</filename>
	<path>cheque_jpg.rf.5c4d57d9ad5202c42739e89d016acdfc.jpg</path>
	<source>
		<database>roboflow.ai</database>
	</source>
	<size>
		<width>1000</width>
		<height>400</height>
		<depth>3</depth>
	</size>
	<segmented>0</segmented>
	<object>
		<name>cmc7</name>
		<pose>Unspecified</pose>
		<truncated>0</truncated>
		<difficult>0</difficult>
		<occluded>0</occluded>
		<bndbox>
			<xmin>163</xmin>
			<xmax>695</xmax>
			<ymin>258</ymin>
			<ymax>310</ymax>
		</bndbox>
	</object>
	<object>
		<name>cmc7box</name>
		<pose>Unspecified</pose>
		<truncated>0</truncated>
		<difficult>0</difficult>
		<occluded>0</occluded>
		<bndbox>
			<xmin>810</xmin>
			<xmax>970</xmax>
			<ymin>134</ymin>
			<ymax>196</ymax>
		</bndbox>
	</object>
	<object>
		<name>sucnum</name>
		<pose>Unspecified</pose>
		<truncated>0</truncated>
		<difficult>0</difficult>
		<occluded>0</occluded>
		<bndbox>
			<xmin>580</xmin>
			<xmax>661</xmax>
			<ymin>99</ymin>
			<ymax>117</ymax>
		</bndbox>
	</object>
	<object>
		<name>sucnum</name>
		<pose>Unspecified</pose>
		<truncated>0</truncated>
		<difficult>0</difficult>
		<occluded>0</occluded>
		<bndbox>
			<xmin>577</xmin>
			<xmax>685</xmax>
			<ymin>114</ymin>
			<ymax>127</ymax>
		</bndbox>
	</object>
	<object>
		<name>accnum</name>
		<pose>Unspecified</pose>
		<truncated>0</truncated>
		<difficult>0</difficult>
		<occluded>0</occluded>
		<bndbox>
			<xmin>252</xmin>
			<xmax>409</xmax>
			<ymin>204</ymin>
			<ymax>221</ymax>
		</bndbox>
	</object>
	<object>
		<name>bank</name>
		<pose>Unspecified</pose>
		<truncated>0</truncated>
		<difficult>0</difficult>
		<occluded>0</occluded>
		<bndbox>
			<xmin>63</xmin>
			<xmax>170</xmax>
			<ymin>85</ymin>
			<ymax>252</ymax>
		</bndbox>
	</object>
</annotation>
